[{"_id":{"$objectID":"5a6dec4179832f2dec9dd11d"},"code":"exports = function(fn) {\r\n  let e = this.libs.createElement.bind(this),\r\n    c = this.constants,\r\n    required = this.libs.createRequiredValidator,\r\n    education = e(\"education\", \"Educational History\", \"\", c.ELEMENTTYPE.SECTION, {\r\n      elements: [\r\n        Object.assign(\r\n          e(\r\n            \"history\",\r\n            \"History\",\r\n            \"\",\r\n            c.ELEMENTTYPE.LIST,\r\n            {\r\n              itemTemplate: [\r\n                e(\"name\", \"Name\", \"\", c.ELEMENTTYPE.INPUT, { type: c.INPUTTYPE.TEXT }, [required()]),\r\n                e(\"country\", \"Country\", \"\", c.ELEMENTTYPE.INPUT, { type: c.INPUTTYPE.TEXT }, [required()]),\r\n                e(\"from\", \"From\", \"\", c.ELEMENTTYPE.INPUT, { type: c.INPUTTYPE.DATE, config: { max: c.DATE.TODAY } }, [required()]),\r\n                e(\"to\", \"To\", \"\", c.ELEMENTTYPE.INPUT, { type: c.INPUTTYPE.DATE, config: { max: c.DATE.TODAY } }, [required()]),\r\n                e(\"certificate\", \"Certificate\", \"\", c.ELEMENTTYPE.SELECT, {\r\n                  type: \"PROCESSOR\",\r\n                  mode: c.ENTRYMODE.OBJECTID,\r\n                  config: {\r\n                    value: \"GET_SCHOOLPROGRAMME\"\r\n                  }\r\n                }, [required()])\r\n              ]\r\n            },\r\n            [this.libs.createMinLengthValidator(1, \"You must make atleast one entry.\")]\r\n          ),\r\n          { uid: \"table\" }\r\n        )\r\n      ]\r\n    });\r\n\r\n  setImmediate(fn, null, [education]);\r\n};\r\n","uid":"getEducationHistoryUI","__v":0,"_references":["createElement","createRequiredValidator","createMinLengthValidator"],"_code":"exports = function(fn) {\ntry{\n{\r\n  let e = this.libs.createElement.bind(this),\r\n    c = this.constants,\r\n    required = this.libs.createRequiredValidator,\r\n    education = e(\"education\", \"Educational History\", \"\", c.ELEMENTTYPE.SECTION, {\r\n      elements: [\r\n        Object.assign(\r\n          e(\r\n            \"history\",\r\n            \"History\",\r\n            \"\",\r\n            c.ELEMENTTYPE.LIST,\r\n            {\r\n              itemTemplate: [\r\n                e(\"name\", \"Name\", \"\", c.ELEMENTTYPE.INPUT, { type: c.INPUTTYPE.TEXT }, [required()]),\r\n                e(\"country\", \"Country\", \"\", c.ELEMENTTYPE.INPUT, { type: c.INPUTTYPE.TEXT }, [required()]),\r\n                e(\"from\", \"From\", \"\", c.ELEMENTTYPE.INPUT, { type: c.INPUTTYPE.DATE, config: { max: c.DATE.TODAY } }, [required()]),\r\n                e(\"to\", \"To\", \"\", c.ELEMENTTYPE.INPUT, { type: c.INPUTTYPE.DATE, config: { max: c.DATE.TODAY } }, [required()]),\r\n                e(\"certificate\", \"Certificate\", \"\", c.ELEMENTTYPE.SELECT, {\r\n                  type: \"PROCESSOR\",\r\n                  mode: c.ENTRYMODE.OBJECTID,\r\n                  config: {\r\n                    value: \"GET_SCHOOLPROGRAMME\"\r\n                  }\r\n                }, [required()])\r\n              ]\r\n            },\r\n            [this.libs.createMinLengthValidator(1, \"You must make atleast one entry.\")]\r\n          ),\r\n          { uid: \"table\" }\r\n        )\r\n      ]\r\n    });\r\n\r\n  setImmediate(fn, null, [education]);\r\n}\n} catch(e){\n//an unexpected error has just occurred. \n fn(e);}};\r\n"}]
