[{"_id":{"$objectID":"59aa7b4ed5faa4219026bad8"},"stepType":"CLIENT","form":{"elements":[{"_id":{"$objectID":"59aa7b4ed5faa4219026bad7"},"name":"process","label":"Manage a Process","elementType":"DESIGNER","args":{"elements":{"element":{"relationships":{"hasMany":{"asyncValidator":"asyncValidators","validator":"validators"}},"elements":{"template":[{"validators":[],"description":"The type of element","asyncValidators":[],"args":{"items":[{"elements":[],"displayLabel":"Chat Messenger","id":"MESSENGER"},{"elements":[{"name":"commandText","label":"Text","elementType":"INPUT","validators":[],"description":"","asyncValidators":[],"component_uid":"8971241b-ecb1-4a0c-9126-645553ec0f5d"},{"name":"commandIcon","label":"Icon","elementType":"INPUT","validators":[],"description":"","asyncValidators":[],"component_uid":"1902241b-ecb1-4a0c-9126-645553ec0f5d"},{"name":"commandProcessor","label":"Processor","validators":[],"description":"","asyncValidators":[],"elementType":"SELECT","args":{"type":"PROCESSOR","config":{"value":{"$objectID":"59aa7b4dd5faa4219026bab1"}}},"component_uid":"2e2a0aba-14e3-01de-a523-272aaae662e5"}],"displayLabel":"Command","id":"COMMAND"},{"id":"WEBVIEW","displayLabel":"Web View","elements":[{"name":"url","label":"Url","elementType":"INPUT","validators":[],"description":"","asyncValidators":[],"component_uid":"8971241b-ecb1-4a2b-8124-645553ec0f5d"}]},{"id":"HTMLVIEW","displayLabel":"HTML View","elements":[{"name":"html","label":"HTML","elementType":"SCRIPT","validators":[],"description":"","asyncValidators":[],"args":{"type":"ejs"},"component_uid":"7ded5b68-ed67-475f-a29a-a9b79d4a4371"}]},{"id":"ACTIONVIEW","displayLabel":"Action View","elements":[{"name":"action","label":"Action processor","validators":[],"description":"","asyncValidators":[],"elementType":"SELECT","args":{"type":"PROCESSOR","config":{"value":{"$objectID":"59aa7b4dd5faa4219026bab1"}}},"component_uid":"2e2a1aaa-34d3-41de-a523-272aaae662e5"},{"name":"elements","label":"Elements supplying action parameters","validators":[],"description":"","asyncValidators":[],"elementType":"LIST","args":{"itemTemplate":{"extension":[{"validators":[],"description":"","asyncValidators":[],"args":{"itemTemplate":{"template_ref":"$validatorTemplate$"}},"name":"validators","label":"Validators","elementType":"LIST","component_uid":"d1660c63-07e5-4be3-8113-12d881bfe080"},{"validators":[],"description":"","asyncValidators":[],"args":{"itemTemplate":{"template_ref":"$asyncValidatorTemplate$"}},"name":"asyncValidators","label":"Asynchronous Validators","elementType":"LIST","component_uid":"90ac61ea-1d69-4ca7-80b2-9e044f0177cc"}],"template_ref":"$elementTemplate$"}},"component_uid":"799a230e-413a-4bde-8af1-710de5629511"},{"name":"commandText","label":"Command Text","validators":[],"description":"","asyncValidators":[],"elementType":"INPUT","component_uid":"f733c806-97b0-4dd7-933d-1dc4df9aa076"}]},{"id":"SCRIPT","displayLabel":"Scripts(i.e Javascript,JSON,EJS)","elements":[{"name":"type","label":"Type (json,Javascript or ejs)","description":"","elementType":"INPUT","validators":[{"validatorType":"REGEX","args":{"value":"/(json|javascript|ejs)/i"}}],"component_uid":"cdf2661b-f591-4235-bf76-09f260b1dec0"}]},{"elements":[],"displayLabel":"Label","id":"LABEL"},{"elements":[],"displayLabel":"Hidden Field (i.e id)","id":"HIDDEN"},{"elements":[{"validators":[],"description":"Text","asyncValidators":[],"name":"text","label":"Text (visible to client.)","elementType":"INPUT","component_uid":"53c11031-a670-4762-896c-1ac38b137c85"},{"validators":[],"description":"","asyncValidators":[],"args":{"type":"text"},"name":"params","label":"Params (pipe delimited strings, e.g name=chidi|number=8|height=23) ","elementType":"INPUT","component_uid":"2069779d-dd19-4esc-b00f-a970a7e2ee80"},{"validators":[],"description":"","asyncValidators":[],"args":{"items":[{"elements":[{"validators":[],"description":"","asyncValidators":[],"args":{"config":{"value":{"$objectID":"59aa7b4dd5faa4219026bab3"}},"type":"PROCESSOR"},"name":"value","label":"Select a Dynamo Process","elementType":"SELECT","component_uid":"1e70e1ef-06fb-49a4-8660-be9d7f69537a"}],"displayLabel":"Link to a Dynamo process/view","id":"DYNAMO"},{"elements":[{"validators":[],"description":"","asyncValidators":[],"args":{"type":"text"},"name":"value","label":"Client Process UID","elementType":"INPUT","component_uid":"2269779d-dd09-4edc-b06f-a970a7e2ee84"}],"displayLabel":"Link to a Client Side Process","id":"CLIENT"}],"path":"config"},"name":"type","label":"Type","elementType":"SELECTSET","component_uid":"af0d275c-ac2d-454b-9d1a-710683b16dd6"}],"displayLabel":"Navigation","id":"NAV"},{"elements":[{"validators":[],"description":"","asyncValidators":[],"args":{"type":"text"},"name":"fileType","label":"Allowed file extensions","elementType":"INPUT","component_uid":"dea39e03-734a-406d-8946-beb997521392"},{"validators":[],"description":"","asyncValidators":[],"args":{"type":"checkbox"},"name":"showPreview","label":"Show Preview","elementType":"INPUT","component_uid":"886cc171-b801-4a74-a69f-58c6b4e97507"}],"displayLabel":"File Upload","id":"FILEUPLOAD"},{"elements":[{"validators":[],"description":"","asyncValidators":[],"args":{"optional":true,"itemTemplate":{"extension":[{"validators":[],"description":"","asyncValidators":[],"args":{"itemTemplate":{"template_ref":"$validatorTemplate$"}},"name":"validators","label":"Validators","elementType":"LIST","component_uid":"76541c51-f25b-4f2f-99e1-54220e3d32ef"},{"validators":[],"description":"","asyncValidators":[],"args":{"itemTemplate":{"template_ref":"$asyncValidatorTemplate$"}},"name":"asyncValidators","label":"Asynchronous Validators","elementType":"LIST","component_uid":"42e7caa0-c9a0-442a-a5c8-48e86a816f33"}],"template_ref":"$elementTemplate$"}},"name":"filter","label":"Items used to filter the grid","elementType":"LIST","component_uid":"19852d9f-2964-45b3-ae53-88a96f139f24"},{"validators":[],"description":"","asyncValidators":[],"args":{"type":"number"},"name":"pageCount","label":"Page Count","elementType":"INPUT","component_uid":"909da233-a4ea-4d45-bb77-3cda5e5da264"},{"validators":[],"description":"","asyncValidators":[],"args":{"itemTemplate":[{"validators":[],"description":"","asyncValidators":[],"args":{"config":{"value":{"$objectID":"59aa7b4dd5faa4219026bab1"}},"type":"PROCESSOR"},"name":"commandProcessor","label":"Processor for running stuff on the server.","elementType":"SELECT","component_uid":"ee45df72-a390-413f-99c4-0ad6f3ob2e12"},{"validators":[],"description":"","asyncValidators":[],"args":{"type":"text"},"name":"commandText","label":"Command Text","elementType":"INPUT","component_uid":"900ca213-a4ea-4d45-bb77-3cda5e5dai204"},{"validators":[],"description":"","asyncValidators":[],"args":{"type":"text"},"name":"commandIcon","label":"Command Icon","elementType":"INPUT","component_uid":"908da233-a4ea-4d45-bb77-3cda5e5da360"}]},"name":"filterCommands","label":"Commands that will be displayed to user as part of filter","elementType":"LIST","component_uid":"eu40df72-a891-403f-99c4-8cd6f3fb2i07"},{"validators":[],"description":"","asyncValidators":[],"args":{"config":{"value":{"$objectID":"59aa7b4dd5faa4219026bab1"}},"type":"PROCESSOR"},"name":"filterProcessor","label":"Processor returns the UI for filter","elementType":"SELECT","component_uid":"ee45df72-a390-413f-99c4-8cd6f3fb2e05"},{"validators":[],"description":"","asyncValidators":[],"args":{"items":[{"elements":[],"displayLabel":"Default","id":"DEFAULT"},{"elements":[{"validators":[],"description":"","asyncValidators":[],"args":{"itemTemplate":{"extension":[{"validators":[],"description":"","asyncValidators":[],"args":{"itemTemplate":{"template_ref":"$validatorTemplate$"}},"name":"validators","label":"Validators","elementType":"LIST","component_uid":"f453bfdb-ed14-4ed5-9743-8cf3b3cd1a97"},{"validators":[],"description":"","asyncValidators":[],"args":{"itemTemplate":{"template_ref":"$asyncValidatorTemplate$"}},"name":"asyncValidators","label":"Asynchronous Validators","elementType":"LIST","component_uid":"93bf7128-d21c-46c7-b33b-7568396f068a"}],"template_ref":"$elementTemplate$"}},"name":"createTemplate","label":"Create Template","elementType":"LIST","component_uid":"9310b539-73c3-4641-8836-74546bd734c7"},{"validators":[],"description":"","asyncValidators":[],"args":{"config":{"value":{"$objectID":"59aa7b4dd5faa4219026bab1"}},"type":"PROCESSOR"},"name":"createProcessor","label":"Processor that will create object","elementType":"SELECT","component_uid":"bf9c506b-c0a2-4c14-8c71-620bf700fc92"},{"validators":[],"description":"","asyncValidators":[],"args":{"optional":true,"itemTemplate":{"extension":[{"validators":[],"description":"","asyncValidators":[],"args":{"itemTemplate":{"template_ref":"$validatorTemplate$"}},"name":"validators","label":"Validators","elementType":"LIST","component_uid":"f7433b0b-b3b9-45f6-8c32-b2f4ad9cc626"},{"validators":[],"description":"","asyncValidators":[],"args":{"itemTemplate":{"template_ref":"$asyncValidatorTemplate$"}},"name":"asyncValidators","label":"Asynchronous Validators","elementType":"LIST","component_uid":"84af9b80-5893-4903-a01b-e5c2c8c6ad1e"}],"template_ref":"$elementTemplate$"}},"name":"editTemplate","label":"Edit Template","elementType":"LIST","component_uid":"2e239609-48e3-4c58-9635-56e7b47a7beb"},{"validators":[],"description":"","asyncValidators":[],"args":{"optional":true,"config":{"value":{"$objectID":"59aa7b4dd5faa4219026bab1"}},"type":"PROCESSOR"},"name":"editProcessor","label":"Processor that will edit object","elementType":"SELECT","component_uid":"e804967f-f5f8-4c36-901b-a74487507987"},{"validators":[],"description":"","asyncValidators":[],"args":{"config":{"value":{"$objectID":"59aa7b4dd5faa4219026bab1"}},"type":"PROCESSOR"},"name":"fetchSingleItemProcessor","label":"Processor that will fetch object before editing","elementType":"SELECT","component_uid":"2c71468c-2d5d-4ac8-bab4-17d31d0567a5"},{"validators":[],"description":"","asyncValidators":[],"args":{"config":{"value":{"$objectID":"59aa7b4dd5faa4219026bab1"}},"type":"PROCESSOR"},"name":"fetchTemplateProcessor","label":"Processor that will fetch template before creating/editing","elementType":"SELECT","component_uid":"52b452b0-3dd7-4499-9f83-ead26dcdf823"}],"displayLabel":"CRUD (Create/Edit/Update Templates required)","id":"CRUD"},{"id":"EDITONLY","displayLabel":"Edit only","elements":[{"validators":[],"description":"","asyncValidators":[],"args":{"config":{"value":{"$objectID":"59aa7b4dd5faa4219026bab1"}},"type":"PROCESSOR"},"name":"editProcessor","label":"Processor that will save after editing","elementType":"SELECT","component_uid":"8118fd9f-0d2c-49c4-99a8-6e6372ffe2a7"},{"validators":[],"description":"","asyncValidators":[],"args":{"config":{"value":{"$objectID":"59aa7b4dd5faa4219026bab1"}},"type":"PROCESSOR"},"name":"fetchTemplateProcessor","label":"Processor that will fetch template before creating/editing","elementType":"SELECT","component_uid":"42c01754-6b09-4068-8ee6-345f0fcf0ec0"},{"validators":[],"description":"","asyncValidators":[],"args":{"config":{"value":{"$objectID":"59aa7b4dd5faa4219026bab1"}},"type":"PROCESSOR"},"name":"fetchSingleItemProcessor","label":"Processor that will fetch object before editing","elementType":"SELECT","component_uid":"9a7ac2f8-bd21-45c0-bb40-dafbfe566668"},{"validators":[],"description":"","asyncValidators":[],"args":{"optional":true,"itemTemplate":{"extension":[{"validators":[],"description":"","asyncValidators":[],"args":{"itemTemplate":{"template_ref":"$validatorTemplate$"}},"name":"validators","label":"Validators","elementType":"LIST","component_uid":"a2290282-0ab3-4897-a0b1-0c1521aac7f7"},{"validators":[],"description":"","asyncValidators":[],"args":{"itemTemplate":{"template_ref":"$asyncValidatorTemplate$"}},"name":"asyncValidators","label":"Asynchronous Validators","elementType":"LIST","component_uid":"b0a3d170-c9d4-4e8a-aac1-c1614e568dbb"}],"template_ref":"$elementTemplate$"}},"name":"editTemplate","label":"Edit Template","elementType":"LIST","component_uid":"401ac7fc-3e74-4e12-a444-7735789ba701"}]}],"path":"extra"},"name":"mode","label":"Grid mode (CRUD expects Create/Edit/Update Templates)","elementType":"SELECTSET","component_uid":"b4809f7a-3390-49b1-bc2d-8d63e099c2d8"},{"validators":[],"description":"List of commands to attach to grid items.","asyncValidators":[],"args":{"optional":true,"itemTemplate":[{"validators":[],"description":"","asyncValidators":[],"args":{"items":[{"elements":[{"validators":[],"description":"","asyncValidators":[],"args":{"config":{"value":{"$objectID":"59aa7b4dd5faa4219026bab1"}},"type":"PROCESSOR"},"name":"value","label":"Select a Processor","elementType":"SELECT","component_uid":"59506fd7-d2ea-40ae-a4c8-300cc7d9e413"}],"displayLabel":"Processor","id":"PROCESSOR"},{"elements":[{"validators":[],"description":"","asyncValidators":[],"args":{"config":{"value":{"$objectID":"59aa7b4dd5faa4219026bab3"}},"type":"PROCESSOR"},"name":"value","label":"Select a Process to navigate to","elementType":"SELECT","component_uid":"e6cf2717-807c-451f-b70d-c211941ebab1"}],"displayLabel":"Navigation Link","id":"NAV"}],"path":"command"},"name":"commandType","label":"Command Type","elementType":"SELECTSET","component_uid":"bb8ec25a-68a0-465e-8e82-0fa6130db334"},{"validators":[],"description":"","asyncValidators":[],"args":{"type":"text"},"name":"commandText","label":"Command Text","elementType":"INPUT","component_uid":"3663b495-091b-4fcd-bc23-82570216be8e"},{"validators":[],"description":"","asyncValidators":[],"name":"commandIcon","label":"Command Icon","elementType":"INPUT","component_uid":"2a6c3534-b3c9-41a5-830e-c3fd2c2b3980"}]},"name":"commands","label":"Commands","elementType":"LIST","component_uid":"75615e20-78a7-480b-aefb-229805e18420"},{"validators":[],"description":"This returns the items to display. The processor must be paginatable","asyncValidators":[],"args":{"config":{"value":{"$objectID":"59aa7b4dd5faa4219026bab1"}},"type":"PROCESSOR"},"name":"source","label":"Source","elementType":"SELECT","component_uid":"1e2b08b6-1943-4915-ac4e-2eeda0f18026"},{"validators":[],"description":"","asyncValidators":[],"args":{"type":"JSON"},"name":"gridArgs","label":"Arguments (passed to all processors)","elementType":"SCRIPT","component_uid":"db54a510-42bc-41ba-81f4-dd173f90d7fe"},{"validators":[],"description":"","asyncValidators":[],"name":"templateConfig","label":"Template (JSON representing template/template config e.g {\"name\":\"basic\",\"config\":{name:\"Name\"}})","elementType":"SCRIPT","component_uid":"3d5fd2a5-3725-41c9-bd2d-8b84ae39d416"}],"displayLabel":"Grid","id":"GRID"},{"elements":[{"validators":[],"description":"","asyncValidators":[],"args":{"items":[{"elements":[{"validators":[],"description":"","asyncValidators":[],"args":{"type":"text"},"name":"data","label":"Url","elementType":"INPUT","component_uid":"21cce951-f2e6-4512-9c3b-72cd14e8ef43"}],"displayLabel":"Link","id":"URL"},{"elements":[{"validators":[],"description":"","asyncValidators":[],"args":{"type":"text"},"name":"data","label":"Identifier","elementType":"INPUT","component_uid":"4d90b101-8698-41b5-bde0-ff1bab9d4b1a"}],"displayLabel":"Relative (Client will provide image)","id":"REL"},{"elements":[{"validators":[],"description":"","asyncValidators":[],"args":{"type":"text"},"name":"data","label":"Base64 Image String","elementType":"INPUT","component_uid":"eecf657c-9942-4a84-a12f-7f00510c0631"}],"displayLabel":"Image data as a base64 URL","id":"DATA"}],"path":"config"},"name":"type","label":"Type of Image","elementType":"SELECTSET","component_uid":"48eae9be-11e6-4565-a6cb-d3c1063d9166"}],"displayLabel":"Image","id":"IMAGE"},{"elements":[{"validators":[],"description":"The user interface uses this value to determine what type of input","asyncValidators":[],"args":{"path":"config","processor":{"$objectID":"59aa7b4dd5faa4219026bab5"}},"name":"type","label":"Type of Input","elementType":"SELECTSET","component_uid":"c0986f50-2a94-4b67-adf6-65f4182591a1"}],"displayLabel":"Input","id":"INPUT"},{"elements":[{"validators":[],"description":"The user interface uses this value to determine the available types","asyncValidators":[],"args":{"items":[{"elements":[{"validators":[],"description":"This the name of the element that represents the source","asyncValidators":[],"name":"value","label":"Name of Element","elementType":"INPUT","component_uid":"0499e946-2e94-4328-8b69-8b5fababb0e0"},{"validators":[],"description":"Property of the element that contains list to bind to.","asyncValidators":[],"name":"path","label":"Property to bind to.","elementType":"INPUT","component_uid":"5882ac79-8587-4172-a6ec-3fa8502bac00"}],"displayLabel":"Another Element in the form.","id":"FORM"},{"elements":[{"validators":[],"description":"","asyncValidators":[],"args":{"config":{"value":{"$objectID":"59aa7b4dd5faa4219026bab1"}},"type":"PROCESSOR"},"name":"value","label":"Value","elementType":"SELECT","component_uid":"c4a431e4-3657-4c7e-b1a5-f1389e0b9b9d"},{"validators":[],"description":"","asyncValidators":[],"name":"customArgs","label":"Custom Arguments","elementType":"SCRIPT","component_uid":"bb609e4b-02cd-41dc-907b-d2297b3926cd"}],"displayLabel":"Processor","id":"PROCESSOR"}],"path":"config"},"name":"type","label":"Type of Select","elementType":"SELECTSET","component_uid":"3b38d799-a749-420c-b5c7-215020475210"},{"name":"mode","label":"Mode of Select","elementType":"SELECTSET","component_uid":"3b38d799-a749-420c-b5c7-215020575019","args":{"items":[{"displayLabel":"Default","id":""},{"displayLabel":"ObjectId","id":"ObjectId"}]}}],"displayLabel":"Select","id":"SELECT"},{"elements":[{"validators":[],"description":"Processors will use this path to refer to items contained here","asyncValidators":[],"args":{"type":"text"},"name":"path","label":"Path","elementType":"INPUT","component_uid":"b0ccd223-2761-44a3-947a-44d87f833a5f"},{"name":"processor","validators":[],"description":"Processor","label":"Processor (overrides items)","asyncValidators":[],"args":{"type":"PROCESSOR","config":{"value":{"$objectID":"59aa7b4dd5faa4219026bab1"}}},"elementType":"SELECT","component_uid":"df99007f-a9c7-4060-a121-c3f1d0f97c5b"},{"name":"processorArgs","validators":[],"description":"ProcessorArgs","label":"Processor Args","asyncValidators":[],"elementType":"SCRIPT","component_uid":"46c2215c-fe16-4807-b7d3-ed57af0832d0"},{"validators":[],"description":"Options under groups.","asyncValidators":[],"args":{"itemTemplate":[{"validators":[],"description":"This is what is sent back to the processor as the value of this field","asyncValidators":[],"name":"id","label":"Result of Selection","elementType":"INPUT","component_uid":"2ff71bba-cce2-4014-9637-6ad0368c2314"},{"validators":[],"description":"","asyncValidators":[],"name":"displayLabel","label":"Label displayed to user","elementType":"INPUT","component_uid":"cef5af70-c3e5-4940-b361-97e9c7a11288"},{"validators":[],"description":"","asyncValidators":[],"args":{"itemTemplate":{"extension":[{"validators":[],"description":"","asyncValidators":[],"args":{"itemTemplate":{"template_ref":"$validatorTemplate$"}},"name":"validators","label":"Validators","elementType":"LIST","component_uid":"e50d2ad5-db21-45a9-a7dd-d9851ef8dae8"},{"validators":[],"description":"","asyncValidators":[],"args":{"itemTemplate":{"template_ref":"$asyncValidatorTemplate$"}},"name":"asyncValidators","label":"Asynchronous Validators","elementType":"LIST","component_uid":"6a0848f5-2539-4219-920c-57ecc7e68c75"}],"template_ref":"$elementTemplate$"}},"name":"elements","label":"Properties to add","elementType":"LIST","component_uid":"654415d5-cb11-4d05-bf18-c9ffc4e80b16"}]},"name":"items","label":"Options","elementType":"LIST","component_uid":"2b096c57-c7f3-49ca-a6cb-16cbf44225a6"},{"name":"mode","label":"Mode of Option Group","elementType":"SELECTSET","component_uid":"3b38d799-a749-420c-b5c7-113010575029","args":{"items":[{"displayLabel":"Default","id":""},{"displayLabel":"ObjectId","id":"ObjectId"}]}}],"displayLabel":"Option Groups","id":"SELECTSET"},{"elements":[{"validators":[],"description":"Template used to create and edit items in this list","asyncValidators":[],"args":{"itemTemplate":{"extension":[{"validators":[],"description":"","asyncValidators":[],"args":{"itemTemplate":{"template_ref":"$validatorTemplate$"}},"name":"validators","label":"Validators","elementType":"LIST","component_uid":"4babed8e-bf01-4363-a274-196f535add2c"},{"validators":[],"description":"","asyncValidators":[],"args":{"itemTemplate":{"template_ref":"$asyncValidatorTemplate$"}},"name":"asyncValidators","label":"Asynchronous Validators","elementType":"LIST","component_uid":"1414a1ec-3ce7-4478-bd9b-d454cedb707a"}],"template_ref":"$elementTemplate$"}},"name":"itemTemplate","label":"Template","elementType":"LIST","component_uid":"14ae0128-d4e4-4e95-9a9f-da93c6409a88"},{"validators":[],"description":"Specific options that affects the lists behavior","asyncValidators":[],"args":{"items":[{"elements":[{"validators":[],"description":"","asyncValidators":[],"args":{"type":"text"},"name":"dynamo_ref","label":"Tag","elementType":"INPUT","component_uid":"769d9ae1-1e3f-46ae-919d-8a9171c4ab70"}],"displayLabel":"Tag Template","id":"TAG"},{"elements":[{"validators":[],"description":"The item template with the referenced tag will override the configured template if found.","asyncValidators":[],"name":"description","label":"","elementType":"LABEL","component_uid":"9d120e56-e3ad-4cfd-82b9-bf59628ddc6b"},{"validators":[],"description":"","asyncValidators":[],"args":{"type":"text"},"name":"template_ref","label":"Referenced Tag","elementType":"INPUT","component_uid":"af274f91-7065-4093-8534-d6291e0f2e4e"},{"validators":[],"description":"","asyncValidators":[],"args":{"itemTemplate":{"extension":[{"validators":[],"description":"","asyncValidators":[],"args":{"itemTemplate":{"template_ref":"$validatorTemplate$"}},"name":"validators","label":"Validators","elementType":"LIST","component_uid":"7e57e63d-95e0-445f-84c5-eee2faf45cf4"},{"validators":[],"description":"","asyncValidators":[],"args":{"itemTemplate":{"template_ref":"$asyncValidatorTemplate$"}},"name":"asyncValidators","label":"Asynchronous Validators","elementType":"LIST","component_uid":"1923fee5-404b-4373-95db-a2fc25b5cadb"}],"template_ref":"$elementTemplate$"}},"name":"extension","label":"Extensions (additional UI components)","elementType":"LIST","component_uid":"1aff916c-773b-4af3-b5ca-1ed54d7d9e97"}],"displayLabel":"Reference a Tag","id":"REF"}],"path":"behavior"},"name":"options","label":"Options","elementType":"SELECTSET","component_uid":"d1dc4d37-1a1c-4185-9310-a6f7ffe28878"},{"name":"disabled","label":"Disabled (Not editable)","elementType":"INPUT","asyncValidators":[],"validators":[],"description":"Toggle list editability","args":{"type":"checkbox"},"component_uid":"c5045ae9-53d3-41f0-9e6c-eca161943b9e"},{"name":"listItemDataTemplateProcessor","validators":[],"description":"Processor","label":"List item data template processor","asyncValidators":[],"args":{"type":"PROCESSOR","config":{"value":{"$objectID":"59aa7b4dd5faa4219026bab1"}}},"elementType":"SELECT","component_uid":"df99007f-a9c7-4060-a121-c3f1d0f90c59"},{"args":{"type":"JSON"},"validators":[],"description":"","asyncValidators":[],"name":"rowTemplate","label":"Template (JSON representing template/template config e.g {\"name\":\"basic\",\"config\":{name:\"Name\"}})","elementType":"SCRIPT","component_uid":"3d5fd2a5-3725-41c9-bd2d-8b84ar39d406"}],"displayLabel":"List","id":"LIST"},{"elements":[{"validators":[],"description":"Elements in the section","asyncValidators":[],"args":{"itemTemplate":{"extension":[{"validators":[],"description":"","asyncValidators":[],"args":{"itemTemplate":{"template_ref":"$validatorTemplate$"}},"name":"validators","label":"Validators","elementType":"LIST","component_uid":"0f7f03ed-2357-4a5c-ae77-48f64470a0f6"},{"validators":[],"description":"","asyncValidators":[],"args":{"itemTemplate":{"template_ref":"$asyncValidatorTemplate$"}},"name":"asyncValidators","label":"Asynchronous Validators","elementType":"LIST","component_uid":"9a5b54f7-dd19-45e0-a16c-df1b0143ac0a"}],"template_ref":"$elementTemplate$"}},"name":"elements","label":"Elements in the section","elementType":"LIST","component_uid":"19c6d843-3212-41bd-932d-930a27d38830"}],"displayLabel":"Section","id":"SECTION"}],"path":"args"},"name":"elementType","label":"Element type","elementType":"SELECTSET","component_uid":"d341fbfa-df57-453f-82f2-df5bb740fd2a"},{"validators":[],"description":"This is the name processors use when sending requests","asyncValidators":[],"name":"name","label":"Name","elementType":"INPUT","component_uid":"860d09e2-c1ee-4612-8e6f-0e72c0508602"},{"validators":[],"description":"This is the item used to display placeholder text for elements","asyncValidators":[],"name":"label","label":"Label","elementType":"INPUT","component_uid":"1f764b19-ac88-44b4-bdd2-c5ac1f1ff04b"},{"validators":[],"description":"","asyncValidators":[],"args":{"type":"number"},"name":"order","label":"Display (tells the container where to place this element)","elementType":"INPUT","component_uid":"0d7c13bb-eb8a-4ae1-a6f6-691c68eb108e"},{"validators":[],"description":"","asyncValidators":[],"name":"uid","label":"Unique Identifier (possibly used to customize the appearance on clientside","elementType":"INPUT","component_uid":"109aa8c1-ab30-4f75-bd57-b1b8143b2cf5"},{"validators":[],"description":"Explanation of elements purpose","asyncValidators":[],"name":"description","label":"Description","elementType":"INPUT","component_uid":"10c26dce-f386-4e6d-85f1-d9b41c8d5dbd"},{"validators":[],"description":"Unique id for every component","asyncValidators":[],"name":"component_uid","label":"Component Unique ID","elementType":"HIDDEN","component_uid":"10c26dce-f380-4e6d-85e1-d9b4108d5dbw"}],"dynamo_ref":"$elementTemplate$"}},"asyncValidator":{"elements":{"template":[{"validators":[],"description":"","asyncValidators":[],"name":"_id","label":"","elementType":"HIDDEN","component_uid":"612ff986-b38e-444d-b4be-7b75aa13b3c3"},{"validators":[],"description":"","asyncValidators":[],"name":"uid","label":"","elementType":"HIDDEN","component_uid":"bde862ca-2105-41ac-9fcd-403deaa6b5ff"},{"validators":[],"description":"Title","asyncValidators":[],"name":"title","label":"Title","elementType":"INPUT","component_uid":"0d9264f4-7b5c-445a-acb0-906ee67bd0d2"},{"validators":[],"description":"Title","asyncValidators":[],"name":"code","label":"This code runs when a client makes a request to the processor endpoint.","elementType":"SCRIPT","component_uid":"3d841f9e-34bf-4b19-aa98-249829ed2223"},{"validators":[],"description":"","asyncValidators":[],"args":{"default":true,"type":"checkbox"},"name":"requiresIdentity","label":"Requires Identity","elementType":"INPUT","component_uid":"dc305590-a209-41f6-95fb-c0f523175829"}],"dynamo_ref":"$asyncValidatorTemplate$"}},"validator":{"elements":{"template":[{"validators":[],"description":"","asyncValidators":[],"args":{"items":[{"elements":[],"displayLabel":"Required","id":"REQUIRED"},{"elements":[{"validators":[],"description":"","asyncValidators":[],"args":{"type":"number"},"name":"max","label":"Max","elementType":"INPUT","component_uid":"c76047ad-8353-4f52-9588-f215e5453a0e"}],"displayLabel":"Maximum Number of Characters","id":"MAXLENGTH"},{"elements":[{"validators":[],"description":"","asyncValidators":[],"args":{"type":"number"},"name":"min","label":"Minimum","elementType":"INPUT","component_uid":"2cc7596a-1fb9-494f-b635-976ded70196e"}],"displayLabel":"Minimum Number of Characters","id":"MINLENGTH"},{"elements":[{"validators":[],"description":"","asyncValidators":[],"args":{"type":"text"},"name":"exp","label":"Expression","elementType":"INPUT","component_uid":"2cc7596a-1fb0-490c-b635-976ded70196e"}],"displayLabel":"Regular Expression","id":"REGEX"}],"path":"args"},"name":"validatorType","label":"Type of Validator","elementType":"SELECTSET","component_uid":"c9acb63b-bf4e-4856-a0be-d5770f4c85c2"},{"validators":[],"description":"","asyncValidators":[],"args":{"type":"text"},"name":"error","label":"Error Message","elementType":"INPUT","component_uid":"c76047ad-8050-ef52-9588-f210e5453v0c"}],"dynamo_ref":"$validatorTemplate$"}},"processor":{"elements":[{"validators":[],"description":"","asyncValidators":[],"name":"_id","label":"","elementType":"HIDDEN","component_uid":"4086437a-150c-4fbf-8b40-6aa7c00857ef"},{"validators":[],"description":"","asyncValidators":[],"name":"uid","label":"","elementType":"HIDDEN","component_uid":"09483262-4416-4fd2-b87a-1f73aeb22281"},{"validators":[],"description":"Title","asyncValidators":[],"name":"title","label":"Title","elementType":"INPUT","component_uid":"6dc993b3-4b87-4b79-82ae-f11f40b2303f"},{"validators":[],"description":"Title","asyncValidators":[],"name":"code","label":"This code runs when a client makes a request to the processor endpoint.","elementType":"SCRIPT","component_uid":"80ea0c1c-0e66-447c-b3ea-b81d56c7efd8"},{"validators":[],"description":"","asyncValidators":[],"args":{"default":true,"type":"checkbox"},"name":"requiresIdentity","label":"Requires Identity","elementType":"INPUT","component_uid":"8e1c1494-1e8d-4637-a1e3-52fb3ba53a55"}]},"form":{"relationships":{"hasMany":{"element":"elements"}},"elements":[{"validators":[],"description":"A form contains elements that are displayed to the user when a step is requested","asyncValidators":[],"name":"description","label":"","elementType":"LABEL","component_uid":"d8e2bace-92e2-4bdc-8f19-2598da333823"}],"hasPreview":true},"existing-step":{"relationships":{},"elements":[{"name":"_id","label":"Step","validators":[],"description":"","asyncValidators":[],"elementType":"SELECT","args":{"type":"PROCESSOR","config":{"value":{"$objectID":"5a6cbf1554197d324063a65d"}}},"component_uid":"2e2a0aba-14e3-01de-a523-272aaae662e5"}]},"existing-processor":{"relationships":{},"elements":[{"name":"_id","label":"Processor","validators":[],"description":"","asyncValidators":[],"elementType":"SELECT","args":{"type":"PROCESSOR","config":{"value":{"$objectID":"59aa7b4dd5faa4219026bab1"}}},"component_uid":"2e2a0abc-00e3-01de-a523-272aaae66205"}]},"step":{"relationships":{"hasMany":{"processor":"processors","existing-processor":"processors"},"has":{"form":"form"}},"elements":[{"validators":[],"description":"","asyncValidators":[],"name":"_id","label":"","elementType":"HIDDEN","component_uid":"3348df55-894b-463c-aa3c-f6cfda7ac64f"},{"validators":[],"description":"","asyncValidators":[],"args":{"items":[{"displayLabel":"Default","id":"PROCESS"},{"displayLabel":"View","id":"VIEW"}]},"name":"mode","label":"Type of Step","elementType":"SELECTSET","component_uid":"e8d3f1cb-9bfc-4997-a731-05d7b13088b1"},{"validators":[],"description":"A step is a single form in a process. Processes can have any number of steps.","asyncValidators":[],"name":"info","label":"","elementType":"LABEL","component_uid":"d8a467c4-4a5f-413b-96ce-51a5113adc0c"},{"validators":[],"description":"Step description","asyncValidators":[],"name":"description","label":"Description of Step","elementType":"INPUT","component_uid":"d8a467c4-4a5f-413b-96ce-51u5013adw0c"},{"validators":[],"description":"Type of Step.","asyncValidators":[],"args":{"default":"CLIENT","disabled":true},"name":"stepType","label":"Type of Step","elementType":"INPUT","component_uid":"16dc2711-2bbb-4ddc-974c-2a0475914a98"}]}},"main":{"relationships":{"hasMany":{"step":{"hasSelect":false,"path":"steps"},"existing-step":{"path":"steps"}},"has":{"processor":"fetchProcessor","existing-processor":"fetchProcessor"}},"elements":[{"validators":[],"description":"","asyncValidators":[],"name":"_id","label":"","elementType":"HIDDEN","component_uid":"bf3ef057-2d29-49b5-8e77-86bcc017c8ee"},{"validators":[],"description":"","asyncValidators":[],"args":{"type":"text"},"name":"uid","label":"Unique Key (used for customization)","elementType":"INPUT","component_uid":"f4b454cc-644e-4a7b-bf65-722bd6e4c903"},{"validators":[],"description":"This is what will be visible to users","asyncValidators":[],"args":{"type":"text"},"name":"title","label":"Title of Process","elementType":"INPUT","component_uid":"b7b83ed6-600f-4727-944d-d7f2cf7940fb"},{"validators":[],"description":"This description what will be visible to users.","asyncValidators":[],"name":"description","label":"Description of Process","elementType":"INPUT","component_uid":"5009f852-fab5-4e4e-a4c2-75341d60cee2"},{"validators":[],"description":"","asyncValidators":[],"args":{"type":"checkbox"},"name":"requiresIdentity","label":"Requires Identity","elementType":"INPUT","component_uid":"116eafa1-7bc5-42b0-aca7-70249096b52f"},{"validators":[],"description":"Additional Information about this process. Only visible to processors","asyncValidators":[],"name":"config","label":"Additional Information","elementType":"SCRIPT","args":{"type":"json"},"component_uid":"5009f852-fab5-4e4e-a4c2-75341d60cee2"}],"name":"process"}},"description":"Used to design/edit processes","validators":[],"asyncValidators":[],"component_uid":"bbf966e5-6220-4e74-9f0e-87acb02e3867"},{"_id":{"$objectID":"59aa7b4ed5faa4219026bad6"},"name":"label","label":"Explanation","elementType":"LABEL","description":"Please enter your password here before clicking save","validators":[],"asyncValidators":[],"component_uid":"492dee88-29d3-437c-9de8-d356854ef02c"},{"_id":{"$objectID":"59aa7b4ed5faa4219026bad5"},"name":"password","label":"Password (Current User)","elementType":"INPUT","args":{"type":"password"},"description":"","validators":[],"asyncValidators":[],"component_uid":"0ca67425-1295-4d38-86e7-301e178e5e5f"},{"_id":{"$objectID":"59aa7b4ed5faa4219026bad4"},"name":"createClaim","label":"Create claim if it does not exist","elementType":"INPUT","args":{"default":true,"type":"checkbox"},"description":"","validators":[],"asyncValidators":[],"component_uid":"9db54cde-e4b9-4bb9-9860-d4210f36cd78"}]},"postprocessors":[],"processors":[{"$objectID":"59aa7b4dd5faa4219026bab8"}],"__v":0}]
