[{"_id":{"$objectID":"5a70b34ea5538a22fc20eabb"},"title":"Fill JUPEB Form","description":"Prospective students fill this form to apply for the JUPEB programme","uid":"JUPEB_FORM","steps":[{"$objectID":"5a70b34ea5538a22fc20eaba"},{"$objectID":"5a70b34ea5538a22fc20eab7"},{"$objectID":"5aba599848660858e0e0d07c"},{"$objectID":"5a6f73486a2ebe20d8e7b741"}],"requiresIdentity":false,"__v":0,"fetchProcessor":{"$objectID":"5a72b60d48dda81fc8cd8f15"},"config":{"review":true,"submitProcessor":"SUBMIT_JUPEB_FORM"},"disableBackwardNavigation":false}]
